amanobot/__init__.py
amanobot/api.py
amanobot/delegate.py
amanobot/exception.py
amanobot/filtering.py
amanobot/helper.py
amanobot/loop.py
amanobot/namedtuple.py
amanobot/routing.py
amanobot/text.py
amanobot/aio/__init__.py
amanobot/aio/api.py
amanobot/aio/delegate.py
amanobot/aio/helper.py
amanobot/aio/loop.py
amanobot/aio/routing.py
amanobot-2.1.0.dist-info/LICENSE.md
amanobot-2.1.0.dist-info/METADATA
amanobot-2.1.0.dist-info/WHEEL
amanobot-2.1.0.dist-info/top_level.txt
amanobot-2.1.0.dist-info/RECORD
