Metadata-Version: 2.1
Name: amanobot
Version: 2.1.0
Summary: Python framework for Telegram Bot API forked from Telepot
Home-page: https://github.com/AmanoTeam/amanobot
Author: AmanoTeam
Author-email: contact@amanoteam.com
License: MIT
Keywords: telegram bot api python wrapper
Platform: UNKNOWN
Classifier: Development Status :: 5 - Production/Stable
Classifier: Intended Audience :: Developers
Classifier: Topic :: Software Development :: Libraries :: Python Modules
Classifier: Topic :: Communications :: Chat
Classifier: License :: OSI Approved :: MIT License
Classifier: Programming Language :: Python :: 3
Classifier: Programming Language :: Python :: 3.5
Classifier: Programming Language :: Python :: 3.6
Classifier: Programming Language :: Python :: 3.7
Classifier: Programming Language :: Python :: 3.8
Classifier: Programming Language :: Python :: 3.9
Requires-Python: >=3.5.3
Requires-Dist: urllib3 (>=1.25.11)
Requires-Dist: aiohttp (>=3.7.2)
